Metadata-Version: 2.1
Name: gb2seq
Version: 0.3.0
Summary: Python library and scripts for working with unannotated sequences based on an annotated reference genome provided by a GenBank file.
Home-page: https://github.com/virologycharite/gb2seq
Download-URL: https://github.com/virologycharite/gb2seq
Author: Terry C. Jones
Author-email: terence.jones@charite.de
Maintainer: Terry C. Jones
Maintainer-email: terence.jones@charite.de
License: MIT
Keywords: GenBank,genetic sequences
Classifier: Programming Language :: Python :: 3.6
Classifier: Programming Language :: Python :: 3.7
Classifier: Programming Language :: Python :: 3.8
Classifier: Programming Language :: Python :: 3.9
Classifier: Programming Language :: Python :: 3.10
Classifier: Programming Language :: Python :: 3.11
Classifier: Development Status :: 4 - Beta
Classifier: Intended Audience :: Developers
Classifier: License :: OSI Approved :: MIT License
Classifier: Operating System :: OS Independent
Classifier: Topic :: Software Development :: Libraries :: Python Modules
License-File: AUTHORS
Requires-Dist: dark-matter>=4.0.68
